{"nftlist":[
    {
        "nft": "NFT20251030000386",
        "site": "PH0600708",
        "area": "PANAY",
        "state": "Processing",
        "severity": "Minor",
        "duration": "0.3",
        "remaining": "7.7",
        "alarm": "Cell out of service",
        "created": "30/10/2025 14:18:00",
        "hour": "14"
    },
    {
        "nft": "NFT20251030000376",
        "site": "PH0600293",
        "area": "NEGROS",
        "state": "Processing",
        "severity": "Major",
        "duration": "0.6",
        "remaining": "7.4",
        "alarm": "Device Offline",
        "created": "30/10/2025 14:00:01",
        "hour": "14"
    },
    {
        "nft": "NFT20251030000370",
        "site": "CO089",
        "area": "CEBU",
        "state": "Finished",
        "severity": "Critical",
        "duration": "-",
        "remaining": "-",
        "alarm": "Over temperature",
        "created": "30/10/2025 13:52:00",
        "hour": "13"
    },
    {
        "nft": "NFT20251030000349",
        "site": "PH0600259",
        "area": "NEGROS",
        "state": "Finished",
        "severity": "Major",
        "duration": "-",
        "remaining": "-",
        "alarm": "Device Offline",
        "created": "30/10/2025 13:17:00",
        "hour": "13"
    },
    {
        "nft": "NFT20251030000347",
        "site": "CO080",
        "area": "NEGROS",
        "state": "Processing",
        "severity": "Major",
        "duration": "1.3",
        "remaining": "6.7",
        "alarm": "Physical Port Down",
        "created": "30/10/2025 13:15:00",
        "hour": "13"
    },
    {
        "nft": "NFT20251030000344",
        "site": "PH0700287",
        "area": "CEBU",
        "state": "Finished",
        "severity": "Major",
        "duration": "-",
        "remaining": "-",
        "alarm": "Device Offline",
        "created": "30/10/2025 13:12:00",
        "hour": "13"
    },
    {
        "nft": "NFT20251030000341",
        "site": "PH0700252",
        "area": "CEBU",
        "state": "Processing",
        "severity": "Major",
        "duration": "1.5",
        "remaining": "6.5",
        "alarm": "Physical Port Down",
        "created": "30/10/2025 13:07:00",
        "hour": "13"
    },
    {
        "nft": "NFT20251030000334",
        "site": "PH0700847",
        "area": "CEBU",
        "state": "Processing",
        "severity": "Minor",
        "duration": "1.8",
        "remaining": "6.2",
        "alarm": "RRU hardware failure",
        "created": "30/10/2025 12:45:00",
        "hour": "12"
    },
    {
        "nft": "NFT20251030000333",
        "site": "PH0600186",
        "area": "PANAY",
        "state": "Finished",
        "severity": "Major",
        "duration": "-",
        "remaining": "-",
        "alarm": "Device Offline",
        "created": "30/10/2025 12:41:00",
        "hour": "12"
    },
    {
        "nft": "NFT20251030000298",
        "site": "PH0700193",
        "area": "CEBU",
        "state": "Finished",
        "severity": "Major",
        "duration": "-",
        "remaining": "-",
        "alarm": "Device Offline",
        "created": "30/10/2025 11:24:00",
        "hour": "11"
    },
    {
        "nft": "NFT20251030000296",
        "site": "PH0700193",
        "area": "CEBU",
        "state": "Finished",
        "severity": "Major",
        "duration": "-",
        "remaining": "-",
        "alarm": "The Device is offline",
        "created": "30/10/2025 11:20:00",
        "hour": "11"
    },
    {
        "nft": "NFT20251030000294",
        "site": "PH0700847",
        "area": "CEBU",
        "state": "Processing",
        "severity": "Minor",
        "duration": "3.3",
        "remaining": "4.7",
        "alarm": "Standing wave warning",
        "created": "30/10/2025 11:15:00",
        "hour": "11"
    },
    {
        "nft": "NFT20251030000290",
        "site": "PH0600293",
        "area": "NEGROS",
        "state": "Finished",
        "severity": "Major",
        "duration": "-",
        "remaining": "-",
        "alarm": "Device Offline",
        "created": "30/10/2025 11:07:00",
        "hour": "11"
    },
    {
        "nft": "NFT20251030000285",
        "site": "IBS0740022",
        "area": "BOHOL",
        "state": "Finished",
        "severity": "Minor",
        "duration": "-",
        "remaining": "-",
        "alarm": "RRU interrupted",
        "created": "30/10/2025 10:56:00",
        "hour": "10"
    },
    {
        "nft": "NFT20251030000281",
        "site": "IBS0740022",
        "area": "BOHOL",
        "state": "Finished",
        "severity": "Major",
        "duration": "-",
        "remaining": "-",
        "alarm": "Pico RRU not connected",
        "created": "30/10/2025 10:54:00",
        "hour": "10"
    },
    {
        "nft": "NFT20251030000262",
        "site": "PH0600300",
        "area": "PANAY",
        "state": "Finished",
        "severity": "Major",
        "duration": "-",
        "remaining": "-",
        "alarm": "Charge Circuit Switch Failure alarm",
        "created": "30/10/2025 10:25:00",
        "hour": "10"
    },
    {
        "nft": "NFT20251030000228",
        "site": "PH0800149",
        "area": "LEYTE",
        "state": "Finished",
        "severity": "Major",
        "duration": "-",
        "remaining": "-",
        "alarm": "Transmission unit link break",
        "created": "30/10/2025 09:59:00",
        "hour": "9"
    },
    {
        "nft": "NFT20251030000214",
        "site": "PH0600285",
        "area": "NEGROS",
        "state": "Finished",
        "severity": "Major",
        "duration": "-",
        "remaining": "-",
        "alarm": "Device Offline",
        "created": "30/10/2025 09:23:00",
        "hour": "9"
    },
    {
        "nft": "NFT20251030000191",
        "site": "PH0800057",
        "area": "LEYTE",
        "state": "Processing",
        "severity": "Major",
        "duration": "5.7",
        "remaining": "2.3",
        "alarm": "Battery Communication Fail",
        "created": "30/10/2025 08:51:00",
        "hour": "8"
    },
    {
        "nft": "NFT20251030000190",
        "site": "PH0600546",
        "area": "NEGROS",
        "state": "Finished",
        "severity": "Major",
        "duration": "-",
        "remaining": "-",
        "alarm": "Device Offline",
        "created": "30/10/2025 08:49:00",
        "hour": "8"
    },
    {
        "nft": "NFT20251030000184",
        "site": "PH0700206",
        "area": "CEBU",
        "state": "Finished",
        "severity": "Major",
        "duration": "-",
        "remaining": "-",
        "alarm": "Battery Communication Fail",
        "created": "30/10/2025 08:42:00",
        "hour": "8"
    },
    {
        "nft": "NFT20251030000180",
        "site": "PH0600285",
        "area": "NEGROS",
        "state": "Finished",
        "severity": "Major",
        "duration": "-",
        "remaining": "-",
        "alarm": "Device Offline",
        "created": "30/10/2025 08:20:00",
        "hour": "8"
    },
    {
        "nft": "NFT20251030000179",
        "site": "PH0700206",
        "area": "CEBU",
        "state": "Finished",
        "severity": "Major",
        "duration": "-",
        "remaining": "-",
        "alarm": "Battery Communication Fail",
        "created": "30/10/2025 08:17:00",
        "hour": "8"
    },
    {
        "nft": "NFT20251030000177",
        "site": "PH0700206",
        "area": "CEBU",
        "state": "Finished",
        "severity": "Major",
        "duration": "-",
        "remaining": "-",
        "alarm": "Battery Communication Fail",
        "created": "30/10/2025 08:11:00",
        "hour": "8"
    },
    {
        "nft": "NFT20251030000171",
        "site": "PH0700193",
        "area": "CEBU",
        "state": "Suspend",
        "severity": "Critical",
        "duration": "3.2",
        "remaining": "0.8",
        "alarm": "The link between the server and the NE is broken",
        "created": "30/10/2025 08:02:00",
        "hour": "8"
    },
    {
        "nft": "NFT20251030000159",
        "site": "PH0600259",
        "area": "NEGROS",
        "state": "Finished",
        "severity": "Major",
        "duration": "-",
        "remaining": "-",
        "alarm": "Device Offline",
        "created": "30/10/2025 07:57:00",
        "hour": "7"
    },
    {
        "nft": "NFT20251030000144",
        "site": "IBS0610007",
        "area": "PANAY",
        "state": "Suspend",
        "severity": "Major",
        "duration": "2.4",
        "remaining": "5.6",
        "alarm": "Pico RRU not connected",
        "created": "30/10/2025 07:31:01",
        "hour": "7"
    },
    {
        "nft": "NFT20251030000120",
        "site": "PH0600825",
        "area": "NEGROS",
        "state": "Finished",
        "severity": "Major",
        "duration": "-",
        "remaining": "-",
        "alarm": "Battery Communication Fail",
        "created": "30/10/2025 06:36:00",
        "hour": "6"
    },
    {
        "nft": "NFT20251030000118",
        "site": "PH0600510",
        "area": "PANAY",
        "state": "Finished",
        "severity": "Major",
        "duration": "-",
        "remaining": "-",
        "alarm": "Battery Communication Fail",
        "created": "30/10/2025 06:31:00",
        "hour": "6"
    },
    {
        "nft": "NFT20251030000117",
        "site": "PH0700382",
        "area": "CEBU",
        "state": "Finished",
        "severity": "Minor",
        "duration": "-",
        "remaining": "-",
        "alarm": "Device Powered Off",
        "created": "30/10/2025 06:29:00",
        "hour": "6"
    },
    {
        "nft": "NFT20251030000115",
        "site": "PH0800144",
        "area": "LEYTE",
        "state": "Finished",
        "severity": "Major",
        "duration": "-",
        "remaining": "-",
        "alarm": "Modem part unlock",
        "created": "30/10/2025 06:17:00",
        "hour": "6"
    },
    {
        "nft": "NFT20251030000086",
        "site": "PH0600030",
        "area": "PANAY",
        "state": "Finished",
        "severity": "Major",
        "duration": "-",
        "remaining": "-",
        "alarm": "Physical Port Down",
        "created": "30/10/2025 05:13:01",
        "hour": "5"
    },
    {
        "nft": "NFT20251030000066",
        "site": "PH0600688",
        "area": "NEGROS",
        "state": "Processing",
        "severity": "Minor",
        "duration": "-5.5",
        "remaining": "13.5",
        "alarm": "Device Powered Off",
        "created": "30/10/2025 04:03:01",
        "hour": "4"
    },
    {
        "nft": "NFT20251030000064",
        "site": "CO038",
        "area": "CEBU",
        "state": "Finished",
        "severity": "Major",
        "duration": "-",
        "remaining": "-",
        "alarm": "Device Offline",
        "created": "30/10/2025 03:54:01",
        "hour": "3"
    },
    {
        "nft": "NFT20251030000056",
        "site": "PH0700245",
        "area": "CEBU",
        "state": "Finished",
        "severity": "Major",
        "duration": "-",
        "remaining": "-",
        "alarm": "Device Offline",
        "created": "30/10/2025 03:11:01",
        "hour": "3"
    },
    {
        "nft": "NFT20251030000053",
        "site": "PH0700330",
        "area": "CEBU",
        "state": "Finished",
        "severity": "Major",
        "duration": "-",
        "remaining": "-",
        "alarm": "Device Offline",
        "created": "30/10/2025 03:05:00",
        "hour": "3"
    },
    {
        "nft": "NFT20251030000052",
        "site": "PH0700881",
        "area": "CEBU",
        "state": "Finished",
        "severity": "Minor",
        "duration": "-",
        "remaining": "-",
        "alarm": "RRU interrupted",
        "created": "30/10/2025 03:03:00",
        "hour": "3"
    },
    {
        "nft": "NFT20251030000045",
        "site": "PH0700096",
        "area": "CEBU",
        "state": "Finished",
        "severity": "Minor",
        "duration": "-",
        "remaining": "-",
        "alarm": "Cell out of service",
        "created": "30/10/2025 02:43:00",
        "hour": "2"
    },
    {
        "nft": "NFT20251030000022",
        "site": "PH0700847",
        "area": "CEBU",
        "state": "Finished",
        "severity": "Minor",
        "duration": "-",
        "remaining": "-",
        "alarm": "Standing wave warning",
        "created": "30/10/2025 02:06:00",
        "hour": "2"
    },
    {
        "nft": "NFT20251030000019",
        "site": "CO038",
        "area": "CEBU",
        "state": "Finished",
        "severity": "Major",
        "duration": "-",
        "remaining": "-",
        "alarm": "Device Offline",
        "created": "30/10/2025 01:45:01",
        "hour": "1"
    },
    {
        "nft": "NFT20251030000018",
        "site": "PH0800144",
        "area": "LEYTE",
        "state": "Finished",
        "severity": "Major",
        "duration": "-",
        "remaining": "-",
        "alarm": "Modem part unlock",
        "created": "30/10/2025 01:42:01",
        "hour": "1"
    },
    {
        "nft": "NFT20251030000016",
        "site": "PH0700198",
        "area": "CEBU",
        "state": "Finished",
        "severity": "Major",
        "duration": "-",
        "remaining": "-",
        "alarm": "Device Offline",
        "created": "30/10/2025 01:32:01",
        "hour": "1"
    },
    {
        "nft": "NFT20251030000005",
        "site": "PH0700198",
        "area": "CEBU",
        "state": "Finished",
        "severity": "Major",
        "duration": "-",
        "remaining": "-",
        "alarm": "Device Offline",
        "created": "30/10/2025 00:26:00",
        "hour": "0"
    },
    {
        "nft": "NFT20251030000022",
        "site": "PH0700847",
        "area": "CEBU",
        "state": "Finished",
        "severity": "Minor",
        "duration": "-",
        "remaining": "-",
        "alarm": "Standing wave warning",
        "created": "30/10/2025 02:06:00",
        "hour": "2"
    },
    {
        "nft": "NFT20251030000019",
        "site": "CO038",
        "area": "CEBU",
        "state": "Finished",
        "severity": "Major",
        "duration": "-",
        "remaining": "-",
        "alarm": "Device Offline",
        "created": "30/10/2025 01:45:01",
        "hour": "1"
    },
    {
        "nft": "NFT20251030000018",
        "site": "PH0800144",
        "area": "LEYTE",
        "state": "Finished",
        "severity": "Major",
        "duration": "-",
        "remaining": "-",
        "alarm": "Modem part unlock",
        "created": "30/10/2025 01:42:01",
        "hour": "1"
    },
    {
        "nft": "NFT20251030000016",
        "site": "PH0700198",
        "area": "CEBU",
        "state": "Finished",
        "severity": "Major",
        "duration": "-",
        "remaining": "-",
        "alarm": "Device Offline",
        "created": "30/10/2025 01:32:01",
        "hour": "1"
    },
    {
        "nft": "NFT20251030000005",
        "site": "PH0700198",
        "area": "CEBU",
        "state": "Finished",
        "severity": "Major",
        "duration": "-",
        "remaining": "-",
        "alarm": "Device Offline",
        "created": "30/10/2025 00:26:00",
        "hour": "0"
    },
    {
        "nft": "NFT20251030000022",
        "site": "PH0700847",
        "area": "CEBU",
        "state": "Finished",
        "severity": "Minor",
        "duration": "-",
        "remaining": "-",
        "alarm": "Standing wave warning",
        "created": "30/10/2025 02:06:00",
        "hour": "2"
    },
    {
        "nft": "NFT20251030000019",
        "site": "CO038",
        "area": "CEBU",
        "state": "Finished",
        "severity": "Major",
        "duration": "-",
        "remaining": "-",
        "alarm": "Device Offline",
        "created": "30/10/2025 01:45:01",
        "hour": "1"
    },
    {
        "nft": "NFT20251030000018",
        "site": "PH0800144",
        "area": "LEYTE",
        "state": "Finished",
        "severity": "Major",
        "duration": "-",
        "remaining": "-",
        "alarm": "Modem part unlock",
        "created": "30/10/2025 01:42:01",
        "hour": "1"
    },
    {
        "nft": "NFT20251030000016",
        "site": "PH0700198",
        "area": "CEBU",
        "state": "Finished",
        "severity": "Major",
        "duration": "-",
        "remaining": "-",
        "alarm": "Device Offline",
        "created": "30/10/2025 01:32:01",
        "hour": "1"
    },
    {
        "nft": "NFT20251030000005",
        "site": "PH0700198",
        "area": "CEBU",
        "state": "Finished",
        "severity": "Major",
        "duration": "-",
        "remaining": "-",
        "alarm": "Device Offline",
        "created": "30/10/2025 00:26:00",
        "hour": "0"
    },
    {
        "nft": "NFT20251030000022",
        "site": "PH0700847",
        "area": "CEBU",
        "state": "Finished",
        "severity": "Minor",
        "duration": "-",
        "remaining": "-",
        "alarm": "Standing wave warning",
        "created": "30/10/2025 02:06:00",
        "hour": "2"
    },
    {
        "nft": "NFT20251030000019",
        "site": "CO038",
        "area": "CEBU",
        "state": "Finished",
        "severity": "Major",
        "duration": "-",
        "remaining": "-",
        "alarm": "Device Offline",
        "created": "30/10/2025 01:45:01",
        "hour": "1"
    },
    {
        "nft": "NFT20251030000018",
        "site": "PH0800144",
        "area": "LEYTE",
        "state": "Finished",
        "severity": "Major",
        "duration": "-",
        "remaining": "-",
        "alarm": "Modem part unlock",
        "created": "30/10/2025 01:42:01",
        "hour": "1"
    },
    {
        "nft": "NFT20251030000016",
        "site": "PH0700198",
        "area": "CEBU",
        "state": "Finished",
        "severity": "Major",
        "duration": "-",
        "remaining": "-",
        "alarm": "Device Offline",
        "created": "30/10/2025 01:32:01",
        "hour": "1"
    },
    {
        "nft": "NFT20251030000005",
        "site": "PH0700198",
        "area": "CEBU",
        "state": "Finished",
        "severity": "Major",
        "duration": "-",
        "remaining": "-",
        "alarm": "Device Offline",
        "created": "30/10/2025 00:26:00",
        "hour": "0"
    }
]}