{"nftlist":[
    {
        "nft": "NFT20260112000355",
        "site": "PH0700015",
        "area": "CEBU",
        "state": "Finished",
        "severity": "Minor",
        "duration": "-",
        "remaining": "-",
        "alarm": "BBU optical module RX and TX abnormal",
        "created": "12/01/2026 15:30:00",
        "hour": "15"
    },
    {
        "nft": "NFT20260112000353",
        "site": "PH0600034",
        "area": "PANAY",
        "state": "Finished",
        "severity": "Minor",
        "duration": "-",
        "remaining": "-",
        "alarm": "Cell out of service",
        "created": "12/01/2026 15:29:00",
        "hour": "15"
    },
    {
        "nft": "NFT20260112000318",
        "site": "PH0700269",
        "area": "CEBU",
        "state": "Processing",
        "severity": "Minor",
        "duration": "3.1",
        "remaining": "4.9",
        "alarm": "Standing wave warning",
        "created": "12/01/2026 14:10:00",
        "hour": "14"
    },
    {
        "nft": "NFT20260112000315",
        "site": "PH0700502",
        "area": "CEBU",
        "state": "Processing",
        "severity": "Major",
        "duration": "3.3",
        "remaining": "4.7",
        "alarm": "Battery Communication Fail",
        "created": "12/01/2026 14:00:01",
        "hour": "14"
    },
    {
        "nft": "NFT20260112000294",
        "site": "PH0600670",
        "area": "PANAY",
        "state": "Suspend",
        "severity": "Minor",
        "duration": "0.4",
        "remaining": "7.6",
        "alarm": "Cell out of service",
        "created": "12/01/2026 13:30:00",
        "hour": "13"
    },
    {
        "nft": "NFT20260112000283",
        "site": "PH0700153",
        "area": "CEBU",
        "state": "Finished",
        "severity": "Major",
        "duration": "-",
        "remaining": "-",
        "alarm": "Device Offline",
        "created": "12/01/2026 13:21:00",
        "hour": "13"
    },
    {
        "nft": "NFT20260112000273",
        "site": "CO085",
        "area": "LEYTE",
        "state": "Finished",
        "severity": "Major",
        "duration": "-",
        "remaining": "-",
        "alarm": "ATS S1 Voltage State",
        "created": "12/01/2026 13:09:00",
        "hour": "13"
    },
    {
        "nft": "NFT20260112000262",
        "site": "PH0700247",
        "area": "CEBU",
        "state": "Finished",
        "severity": "Major",
        "duration": "-",
        "remaining": "-",
        "alarm": "Device Offline",
        "created": "12/01/2026 12:40:24",
        "hour": "12"
    },
    {
        "nft": "NFT20260112000231",
        "site": "PH0700592",
        "area": "BOHOL",
        "state": "Finished",
        "severity": "Minor",
        "duration": "-",
        "remaining": "-",
        "alarm": "Cell out of service",
        "created": "12/01/2026 11:39:00",
        "hour": "11"
    },
    {
        "nft": "NFT20260112000226",
        "site": "PH0600621",
        "area": "PANAY",
        "state": "Processing",
        "severity": "Major",
        "duration": "5.8",
        "remaining": "2.2",
        "alarm": "Battery Communication Fail",
        "created": "12/01/2026 11:30:00",
        "hour": "11"
    },
    {
        "nft": "NFT20260112000221",
        "site": "PH0700021",
        "area": "CEBU",
        "state": "Finished",
        "severity": "Minor",
        "duration": "-",
        "remaining": "-",
        "alarm": "Cell out of service",
        "created": "12/01/2026 11:17:00",
        "hour": "11"
    },
    {
        "nft": "NFT20260112000211",
        "site": "PH0700430",
        "area": "CEBU",
        "state": "Finished",
        "severity": "Major",
        "duration": "-",
        "remaining": "-",
        "alarm": "Device Offline",
        "created": "12/01/2026 10:53:00",
        "hour": "10"
    },
    {
        "nft": "NFT20260112000206",
        "site": "IBS0740014",
        "area": "CEBU",
        "state": "Finished",
        "severity": "Major",
        "duration": "-",
        "remaining": "-",
        "alarm": "Pico RRU not connected",
        "created": "12/01/2026 10:44:00",
        "hour": "10"
    },
    {
        "nft": "NFT20260112000194",
        "site": "PH0700136",
        "area": "NEGROS",
        "state": "Finished",
        "severity": "Major",
        "duration": "-",
        "remaining": "-",
        "alarm": "Device Offline",
        "created": "12/01/2026 10:31:00",
        "hour": "10"
    },
    {
        "nft": "NFT20260112000188",
        "site": "PH0700836",
        "area": "CEBU",
        "state": "Finished",
        "severity": "Minor",
        "duration": "-",
        "remaining": "-",
        "alarm": "BBU optical module RX and TX abnormal",
        "created": "12/01/2026 10:20:00",
        "hour": "10"
    },
    {
        "nft": "NFT20260112000159",
        "site": "",
        "area": "LEYTE",
        "state": "Suspend",
        "severity": "Major",
        "duration": "2.4",
        "remaining": "5.6",
        "alarm": "AC SPD Abnormal",
        "created": "12/01/2026 09:34:00",
        "hour": "9"
    },
    {
        "nft": "NFT20260112000113",
        "site": "CO103",
        "area": "BOHOL",
        "state": "Suspend",
        "severity": "Major",
        "duration": "6.6",
        "remaining": "1.4",
        "alarm": "Cycle equalization alarm",
        "created": "12/01/2026 08:03:00",
        "hour": "8"
    },
    {
        "nft": "NFT20260112000084",
        "site": "IBS0740014",
        "area": "CEBU",
        "state": "Finished",
        "severity": "Minor",
        "duration": "-",
        "remaining": "-",
        "alarm": "RRU interrupted",
        "created": "12/01/2026 07:31:01",
        "hour": "7"
    },
    {
        "nft": "NFT20260112000071",
        "site": "PH0700287",
        "area": "CEBU",
        "state": "Finished",
        "severity": "Major",
        "duration": "-",
        "remaining": "-",
        "alarm": "Device Offline",
        "created": "12/01/2026 07:12:00",
        "hour": "7"
    },
    {
        "nft": "NFT20260112000067",
        "site": "PH0700792",
        "area": "BOHOL",
        "state": "Finished",
        "severity": "Major",
        "duration": "-",
        "remaining": "-",
        "alarm": "Physical Port Down",
        "created": "12/01/2026 06:56:00",
        "hour": "6"
    },
    {
        "nft": "NFT20260112000054",
        "site": "PH0700792",
        "area": "BOHOL",
        "state": "Finished",
        "severity": "Major",
        "duration": "-",
        "remaining": "-",
        "alarm": "Physical Port Down",
        "created": "12/01/2026 05:58:01",
        "hour": "5"
    },
    {
        "nft": "NFT20260112000053",
        "site": "PH0800002",
        "area": "LEYTE",
        "state": "Finished",
        "severity": "Major",
        "duration": "-",
        "remaining": "-",
        "alarm": "Battery Communication Fail",
        "created": "12/01/2026 05:55:00",
        "hour": "5"
    },
    {
        "nft": "NFT20260112000044",
        "site": "PH0700287",
        "area": "CEBU",
        "state": "Finished",
        "severity": "Major",
        "duration": "-",
        "remaining": "-",
        "alarm": "Device Offline",
        "created": "12/01/2026 05:00:01",
        "hour": "5"
    },
    {
        "nft": "NFT20260112000040",
        "site": "PH0700006",
        "area": "CEBU",
        "state": "Finished",
        "severity": "Minor",
        "duration": "-",
        "remaining": "-",
        "alarm": "Device Powered Off",
        "created": "12/01/2026 03:47:00",
        "hour": "3"
    },
    {
        "nft": "NFT20260112000037",
        "site": "PH0700006",
        "area": "CEBU",
        "state": "Finished",
        "severity": "Major",
        "duration": "-",
        "remaining": "-",
        "alarm": "Device Offline",
        "created": "12/01/2026 03:31:01",
        "hour": "3"
    },
    {
        "nft": "NFT20260112000036",
        "site": "PH0600530",
        "area": "NEGROS",
        "state": "Finished",
        "severity": "Critical",
        "duration": "-",
        "remaining": "-",
        "alarm": "The link between the server and the NE is broken",
        "created": "12/01/2026 03:31:00",
        "hour": "3"
    },
    {
        "nft": "NFT20260112000035",
        "site": "PH0600473",
        "area": "NEGROS",
        "state": "Finished",
        "severity": "Major",
        "duration": "-",
        "remaining": "-",
        "alarm": "Transmission unit link break",
        "created": "12/01/2026 03:30:00",
        "hour": "3"
    },
    {
        "nft": "NFT20260112000010",
        "site": "PH0600420",
        "area": "NEGROS",
        "state": "Finished",
        "severity": "Major",
        "duration": "-",
        "remaining": "-",
        "alarm": "Transmission unit link break",
        "created": "12/01/2026 00:32:00",
        "hour": "0"
    },
    {
        "nft": "NFT20260112000009",
        "site": "PH0700287",
        "area": "CEBU",
        "state": "Finished",
        "severity": "Major",
        "duration": "-",
        "remaining": "-",
        "alarm": "Device Offline",
        "created": "12/01/2026 00:31:01",
        "hour": "0"
    },
    {
        "nft": "NFT20260112000004",
        "site": "PH0700006",
        "area": "CEBU",
        "state": "Finished",
        "severity": "Major",
        "duration": "-",
        "remaining": "-",
        "alarm": "BBU interrupted",
        "created": "12/01/2026 00:13:00",
        "hour": "0"
    }
]}